pycheckit/__init__.py
pycheckit/pycheckit.py
python_checkit-1.0.5.dist-info/METADATA
python_checkit-1.0.5.dist-info/WHEEL
python_checkit-1.0.5.dist-info/top_level.txt
python_checkit-1.0.5.dist-info/RECORD
