Metadata-Version: 2.1
Name: python-checkit
Version: 1.0.5
Summary: Checkit API Client
Home-page: https://bitbucket.org/metadonors/python-checkit
Author: Metadonors
Author-email: fabrizio.arzeni@metadonors.it
License: MIT
Platform: UNKNOWN
Requires-Dist: requests
Provides-Extra: dev
Requires-Dist: pytest ; extra == 'dev'
Requires-Dist: pytest-pep8 ; extra == 'dev'
Requires-Dist: pytest-cov ; extra == 'dev'
